[{"id":46,"heiti":"Flokkur fólksins","skammstofun":"Flf","thing":[{"lthing":148,"members":5,"seats":4,"speeches":497,"seconds":80308,"ja":2180,"nei":76,"sat_hja":309,"bodadi_fjarvist":29,"fjarverandi":270,"maeting":0.8956},{"lthing":149,"members":3,"seats":2,"speeches":539,"seconds":94819,"ja":1645,"nei":167,"sat_hja":400,"bodadi_fjarvist":65,"fjarverandi":95,"maeting":0.9325},{"lthing":150,"members":3,"seats":2,"speeches":762,"seconds":130854,"ja":1212,"nei":48,"sat_hja":716,"bodadi_fjarvist":138,"fjarverandi":382,"maeting":0.7917},{"lthing":151,"members":2,"seats":2,"speeches":577,"seconds":123424,"ja":1591,"nei":40,"sat_hja":210,"bodadi_fjarvist":181,"fjarverandi":516,"maeting":0.7254},{"lthing":152,"members":13,"seats":6,"speeches":1021,"seconds":195594,"ja":2284,"nei":92,"sat_hja":685,"bodadi_fjarvist":256,"fjarverandi":1091,"maeting":0.6944},{"lthing":153,"members":10,"seats":6,"speeches":1430,"seconds":282195,"ja":2594,"nei":383,"sat_hja":1326,"bodadi_fjarvist":46,"fjarverandi":739,"maeting":0.8457},{"lthing":154,"members":11,"seats":6,"speeches":1482,"seconds":310484,"ja":4476,"nei":404,"sat_hja":1121,"bodadi_fjarvist":45,"fjarverandi":852,"maeting":0.87},{"lthing":155,"members":6,"seats":5,"speeches":170,"seconds":50084,"ja":372,"nei":29,"sat_hja":182,"bodadi_fjarvist":0,"fjarverandi":226,"maeting":0.7206},{"lthing":156,"members":18,"seats":10,"speeches":890,"seconds":122150,"ja":2339,"nei":243,"sat_hja":3,"bodadi_fjarvist":30,"fjarverandi":385,"maeting":0.8617},{"lthing":157,"members":17,"seats":9,"speeches":1270,"seconds":179445,"ja":8972,"nei":1490,"sat_hja":0,"bodadi_fjarvist":205,"fjarverandi":1433,"maeting":0.8646}]},{"id":2,"heiti":"Framsóknarflokkur","skammstofun":"F","thing":[{"lthing":148,"members":12,"seats":8,"speeches":756,"seconds":123445,"ja":4281,"nei":568,"sat_hja":8,"bodadi_fjarvist":298,"fjarverandi":568,"maeting":0.8487},{"lthing":149,"members":14,"seats":8,"speeches":1282,"seconds":232411,"ja":7501,"nei":951,"sat_hja":5,"bodadi_fjarvist":93,"fjarverandi":938,"maeting":0.8913},{"lthing":150,"members":13,"seats":8,"speeches":1160,"seconds":192096,"ja":7044,"nei":1368,"sat_hja":16,"bodadi_fjarvist":137,"fjarverandi":1419,"maeting":0.8442},{"lthing":151,"members":10,"seats":8,"speeches":996,"seconds":181779,"ja":7661,"nei":1265,"sat_hja":1,"bodadi_fjarvist":57,"fjarverandi":1168,"maeting":0.8793},{"lthing":152,"members":19,"seats":13,"speeches":946,"seconds":151076,"ja":7519,"nei":770,"sat_hja":1,"bodadi_fjarvist":55,"fjarverandi":1301,"maeting":0.8594},{"lthing":153,"members":20,"seats":13,"speeches":1264,"seconds":208130,"ja":7416,"nei":1987,"sat_hja":2,"bodadi_fjarvist":120,"fjarverandi":1499,"maeting":0.8531},{"lthing":154,"members":21,"seats":13,"speeches":1324,"seconds":262828,"ja":11128,"nei":1644,"sat_hja":1,"bodadi_fjarvist":4,"fjarverandi":2127,"maeting":0.857},{"lthing":155,"members":14,"seats":13,"speeches":240,"seconds":41590,"ja":1735,"nei":43,"sat_hja":1,"bodadi_fjarvist":0,"fjarverandi":327,"maeting":0.8447},{"lthing":156,"members":8,"seats":5,"speeches":1889,"seconds":297264,"ja":814,"nei":116,"sat_hja":201,"bodadi_fjarvist":5,"fjarverandi":364,"maeting":0.754},{"lthing":157,"members":9,"seats":5,"speeches":1580,"seconds":273975,"ja":2437,"nei":364,"sat_hja":1976,"bodadi_fjarvist":8,"fjarverandi":1265,"maeting":0.7896}]},{"id":47,"heiti":"Miðflokkurinn","skammstofun":"M","thing":[{"lthing":148,"members":11,"seats":7,"speeches":1049,"seconds":153501,"ja":3660,"nei":297,"sat_hja":557,"bodadi_fjarvist":44,"fjarverandi":454,"maeting":0.9006},{"lthing":149,"members":14,"seats":9,"speeches":4488,"seconds":682543,"ja":5096,"nei":752,"sat_hja":1245,"bodadi_fjarvist":127,"fjarverandi":1082,"maeting":0.8544},{"lthing":150,"members":13,"seats":9,"speeches":1960,"seconds":463889,"ja":5583,"nei":649,"sat_hja":2708,"bodadi_fjarvist":440,"fjarverandi":1852,"maeting":0.7959},{"lthing":151,"members":9,"seats":9,"speeches":1731,"seconds":464287,"ja":7177,"nei":782,"sat_hja":1886,"bodadi_fjarvist":125,"fjarverandi":1451,"maeting":0.862},{"lthing":152,"members":7,"seats":2,"speeches":558,"seconds":108781,"ja":785,"nei":46,"sat_hja":250,"bodadi_fjarvist":18,"fjarverandi":405,"maeting":0.7188},{"lthing":153,"members":4,"seats":2,"speeches":509,"seconds":84729,"ja":476,"nei":175,"sat_hja":323,"bodadi_fjarvist":10,"fjarverandi":712,"maeting":0.5743},{"lthing":154,"members":4,"seats":2,"speeches":411,"seconds":74436,"ja":852,"nei":141,"sat_hja":432,"bodadi_fjarvist":4,"fjarverandi":871,"maeting":0.6196},{"lthing":155,"members":3,"seats":3,"speeches":69,"seconds":9178,"ja":104,"nei":1,"sat_hja":47,"bodadi_fjarvist":0,"fjarverandi":334,"maeting":0.3128},{"lthing":156,"members":13,"seats":8,"speeches":3342,"seconds":555704,"ja":1012,"nei":231,"sat_hja":478,"bodadi_fjarvist":36,"fjarverandi":643,"maeting":0.7171},{"lthing":157,"members":15,"seats":8,"speeches":3399,"seconds":617268,"ja":3949,"nei":1090,"sat_hja":3187,"bodadi_fjarvist":64,"fjarverandi":1390,"maeting":0.8498}]},{"id":43,"heiti":"Píratar","skammstofun":"P","thing":[{"lthing":148,"members":10,"seats":6,"speeches":1338,"seconds":202523,"ja":3280,"nei":185,"sat_hja":538,"bodadi_fjarvist":137,"fjarverandi":146,"maeting":0.934},{"lthing":149,"members":11,"seats":6,"speeches":1693,"seconds":258207,"ja":4480,"nei":427,"sat_hja":1563,"bodadi_fjarvist":172,"fjarverandi":474,"maeting":0.9092},{"lthing":150,"members":8,"seats":6,"speeches":1744,"seconds":286169,"ja":3759,"nei":638,"sat_hja":1942,"bodadi_fjarvist":314,"fjarverandi":835,"maeting":0.8466},{"lthing":151,"members":10,"seats":7,"speeches":1352,"seconds":255000,"ja":4667,"nei":448,"sat_hja":1230,"bodadi_fjarvist":92,"fjarverandi":1177,"maeting":0.8333},{"lthing":152,"members":12,"seats":6,"speeches":2162,"seconds":364700,"ja":2773,"nei":242,"sat_hja":1145,"bodadi_fjarvist":101,"fjarverandi":191,"maeting":0.9344},{"lthing":153,"members":12,"seats":6,"speeches":3242,"seconds":601515,"ja":2635,"nei":452,"sat_hja":1450,"bodadi_fjarvist":193,"fjarverandi":358,"maeting":0.8917},{"lthing":154,"members":14,"seats":6,"speeches":1987,"seconds":365433,"ja":3839,"nei":538,"sat_hja":1422,"bodadi_fjarvist":387,"fjarverandi":714,"maeting":0.8404},{"lthing":155,"members":7,"seats":6,"speeches":187,"seconds":31830,"ja":407,"nei":35,"sat_hja":325,"bodadi_fjarvist":38,"fjarverandi":167,"maeting":0.7891}]},{"id":38,"heiti":"Samfylkingin","skammstofun":"Sf","thing":[{"lthing":148,"members":10,"seats":7,"speeches":897,"seconds":131531,"ja":3867,"nei":176,"sat_hja":401,"bodadi_fjarvist":278,"fjarverandi":290,"maeting":0.8867},{"lthing":149,"members":16,"seats":7,"speeches":1544,"seconds":267234,"ja":5391,"nei":533,"sat_hja":1231,"bodadi_fjarvist":413,"fjarverandi":734,"maeting":0.8618},{"lthing":150,"members":12,"seats":7,"speeches":1369,"seconds":251929,"ja":5298,"nei":459,"sat_hja":2172,"bodadi_fjarvist":135,"fjarverandi":672,"maeting":0.9076},{"lthing":151,"members":8,"seats":8,"speeches":1132,"seconds":220084,"ja":6353,"nei":348,"sat_hja":880,"bodadi_fjarvist":274,"fjarverandi":1028,"maeting":0.8534},{"lthing":152,"members":12,"seats":6,"speeches":1529,"seconds":231537,"ja":2880,"nei":77,"sat_hja":1113,"bodadi_fjarvist":14,"fjarverandi":236,"maeting":0.9421},{"lthing":153,"members":16,"seats":6,"speeches":1281,"seconds":206687,"ja":2965,"nei":370,"sat_hja":1093,"bodadi_fjarvist":235,"fjarverandi":425,"maeting":0.8703},{"lthing":154,"members":12,"seats":6,"speeches":1119,"seconds":196913,"ja":4407,"nei":262,"sat_hja":1349,"bodadi_fjarvist":460,"fjarverandi":422,"maeting":0.8722},{"lthing":155,"members":6,"seats":6,"speeches":115,"seconds":13312,"ja":332,"nei":7,"sat_hja":294,"bodadi_fjarvist":230,"fjarverandi":109,"maeting":0.6512},{"lthing":156,"members":26,"seats":15,"speeches":1680,"seconds":186168,"ja":3655,"nei":395,"sat_hja":1,"bodadi_fjarvist":224,"fjarverandi":225,"maeting":0.9002},{"lthing":157,"members":25,"seats":15,"speeches":2602,"seconds":321340,"ja":13715,"nei":2347,"sat_hja":1,"bodadi_fjarvist":813,"fjarverandi":1274,"maeting":0.885}]},{"id":35,"heiti":"Sjálfstæðisflokkur","skammstofun":"S","thing":[{"lthing":148,"members":21,"seats":16,"speeches":1206,"seconds":197521,"ja":8328,"nei":1107,"sat_hja":111,"bodadi_fjarvist":597,"fjarverandi":1308,"maeting":0.8336},{"lthing":149,"members":22,"seats":16,"speeches":2553,"seconds":435716,"ja":13897,"nei":1771,"sat_hja":91,"bodadi_fjarvist":563,"fjarverandi":2654,"maeting":0.8305},{"lthing":150,"members":24,"seats":16,"speeches":2087,"seconds":338284,"ja":14271,"nei":2853,"sat_hja":128,"bodadi_fjarvist":425,"fjarverandi":2291,"maeting":0.864},{"lthing":151,"members":16,"seats":16,"speeches":1944,"seconds":353594,"ja":14615,"nei":2459,"sat_hja":121,"bodadi_fjarvist":121,"fjarverandi":2988,"maeting":0.8469},{"lthing":152,"members":25,"seats":17,"speeches":1780,"seconds":245706,"ja":9175,"nei":926,"sat_hja":4,"bodadi_fjarvist":246,"fjarverandi":2111,"maeting":0.8109},{"lthing":153,"members":26,"seats":17,"speeches":2470,"seconds":332216,"ja":9397,"nei":2464,"sat_hja":38,"bodadi_fjarvist":326,"fjarverandi":2191,"maeting":0.8254},{"lthing":154,"members":24,"seats":17,"speeches":2206,"seconds":343722,"ja":13673,"nei":2134,"sat_hja":47,"bodadi_fjarvist":356,"fjarverandi":3340,"maeting":0.8109},{"lthing":155,"members":18,"seats":17,"speeches":361,"seconds":54014,"ja":2169,"nei":62,"sat_hja":0,"bodadi_fjarvist":15,"fjarverandi":508,"maeting":0.8101},{"lthing":156,"members":22,"seats":14,"speeches":4584,"seconds":743137,"ja":1982,"nei":426,"sat_hja":638,"bodadi_fjarvist":96,"fjarverandi":1058,"maeting":0.7252},{"lthing":157,"members":23,"seats":14,"speeches":4641,"seconds":854024,"ja":7769,"nei":1614,"sat_hja":3686,"bodadi_fjarvist":104,"fjarverandi":3767,"maeting":0.7715}]},{"id":23,"heiti":"Vinstrihreyfingin - grænt framboð","skammstofun":"Vg","thing":[{"lthing":148,"members":15,"seats":11,"speeches":1290,"seconds":168886,"ja":6415,"nei":779,"sat_hja":47,"bodadi_fjarvist":168,"fjarverandi":467,"maeting":0.9194},{"lthing":149,"members":21,"seats":11,"speeches":2354,"seconds":346326,"ja":10040,"nei":1246,"sat_hja":63,"bodadi_fjarvist":582,"fjarverandi":1115,"maeting":0.8699},{"lthing":150,"members":16,"seats":9,"speeches":2101,"seconds":310158,"ja":10123,"nei":1893,"sat_hja":253,"bodadi_fjarvist":197,"fjarverandi":1262,"maeting":0.8937},{"lthing":151,"members":9,"seats":9,"speeches":1756,"seconds":257618,"ja":9298,"nei":1469,"sat_hja":1,"bodadi_fjarvist":55,"fjarverandi":598,"maeting":0.9428},{"lthing":152,"members":13,"seats":8,"speeches":805,"seconds":119815,"ja":4435,"nei":450,"sat_hja":21,"bodadi_fjarvist":40,"fjarverandi":946,"maeting":0.8327},{"lthing":153,"members":15,"seats":8,"speeches":1137,"seconds":181029,"ja":4538,"nei":1166,"sat_hja":1,"bodadi_fjarvist":147,"fjarverandi":932,"maeting":0.8409},{"lthing":154,"members":13,"seats":8,"speeches":1070,"seconds":190501,"ja":6891,"nei":979,"sat_hja":36,"bodadi_fjarvist":17,"fjarverandi":1277,"maeting":0.8593},{"lthing":155,"members":8,"seats":7,"speeches":181,"seconds":28082,"ja":978,"nei":6,"sat_hja":125,"bodadi_fjarvist":0,"fjarverandi":187,"maeting":0.8557}]},{"id":45,"heiti":"Viðreisn","skammstofun":"V","thing":[{"lthing":148,"members":6,"seats":4,"speeches":795,"seconds":123571,"ja":1628,"nei":120,"sat_hja":176,"bodadi_fjarvist":350,"fjarverandi":590,"maeting":0.6718},{"lthing":149,"members":7,"seats":4,"speeches":1237,"seconds":204370,"ja":2747,"nei":242,"sat_hja":858,"bodadi_fjarvist":146,"fjarverandi":751,"maeting":0.8109},{"lthing":150,"members":6,"seats":4,"speeches":900,"seconds":168597,"ja":2891,"nei":135,"sat_hja":1007,"bodadi_fjarvist":67,"fjarverandi":892,"maeting":0.8079},{"lthing":151,"members":4,"seats":4,"speeches":814,"seconds":159582,"ja":3402,"nei":133,"sat_hja":631,"bodadi_fjarvist":31,"fjarverandi":879,"maeting":0.8207},{"lthing":152,"members":12,"seats":5,"speeches":1301,"seconds":223275,"ja":2324,"nei":128,"sat_hja":812,"bodadi_fjarvist":49,"fjarverandi":309,"maeting":0.9012},{"lthing":153,"members":10,"seats":5,"speeches":1156,"seconds":194907,"ja":2436,"nei":276,"sat_hja":1008,"bodadi_fjarvist":14,"fjarverandi":506,"maeting":0.8774},{"lthing":154,"members":11,"seats":5,"speeches":1028,"seconds":188516,"ja":3573,"nei":210,"sat_hja":1020,"bodadi_fjarvist":6,"fjarverandi":941,"maeting":0.8353},{"lthing":155,"members":6,"seats":5,"speeches":93,"seconds":15229,"ja":317,"nei":5,"sat_hja":74,"bodadi_fjarvist":0,"fjarverandi":413,"maeting":0.4895},{"lthing":156,"members":18,"seats":11,"speeches":1044,"seconds":140293,"ja":2456,"nei":265,"sat_hja":3,"bodadi_fjarvist":91,"fjarverandi":485,"maeting":0.8255},{"lthing":157,"members":25,"seats":11,"speeches":1730,"seconds":263690,"ja":9465,"nei":1663,"sat_hja":1,"bodadi_fjarvist":232,"fjarverandi":1949,"maeting":0.8361}]},{"id":17,"heiti":"utan þingflokka","skammstofun":"U","thing":[{"lthing":149,"members":2,"seats":0,"speeches":910,"seconds":163766,"ja":1538,"nei":182,"sat_hja":447,"bodadi_fjarvist":38,"fjarverandi":167,"maeting":0.9136},{"lthing":150,"members":0,"seats":2,"speeches":0,"seconds":0,"ja":0,"nei":0,"sat_hja":0,"bodadi_fjarvist":0,"fjarverandi":0,"maeting":null},{"lthing":151,"members":2,"seats":0,"speeches":390,"seconds":96398,"ja":1839,"nei":153,"sat_hja":345,"bodadi_fjarvist":19,"fjarverandi":182,"maeting":0.9208},{"lthing":155,"members":0,"seats":1,"speeches":0,"seconds":0,"ja":0,"nei":0,"sat_hja":0,"bodadi_fjarvist":0,"fjarverandi":0,"maeting":null},{"lthing":157,"members":0,"seats":1,"speeches":0,"seconds":0,"ja":0,"nei":0,"sat_hja":0,"bodadi_fjarvist":0,"fjarverandi":0,"maeting":null}]}]